{
  "id": 9,
  "title": "No, that's Soft Tails: MoxieTV Bloopers, season one",
  "body": "In lieu of a new MoxieTV, here's roughly 13 minutes of Dan flubbing his lines. If you've just eaten, you might want to wait a while for your food to settle, unless, of course, you're used to looking at Dan for that long of time.",
  "embed": "<iframe width=\"445\" height=\"331\" src=\"http://www.youtube.com/embed/n741KjuZikY?rel=0\" frameborder=\"0\" allowfullscreen></iframe>",
  "backup": "09.flv",
  "credits": "<ul class=\"credits\">\r\n  <li><b>Director</b>Justin Glow</li>\r\n  <li><b>Host</b>Dan Chilton</li>\r\n  <li><b>Continual asker of \"what are you laughing at?\"</b>Nicole Chilton</li>\r\n</ul>",
  "created_at": "2006-12-12T11:00:00.000Z"
}